cytoskeleton_analyser/__init__.py
cytoskeleton_analyser/cells.py
cytoskeleton_analyser/histograms.py
cytoskeleton_analyser/inout.py
cytoskeleton_analyser/plasma_membrane.py
cytoskeleton_analyser/report.py
cytoskeleton_analyser/summary.py
cytoskeleton_analyser/version.py
cytoskeleton_analyser/visualization.py
cytoskeleton_analyser/config/__init__.py
cytoskeleton_analyser/config/_m1d.py
cytoskeleton_analyser/config/_mtoc.py
cytoskeleton_analyser/config/config.py
cytoskeleton_analyser/config/drivers.py
cytoskeleton_analyser/database/__init__.py
cytoskeleton_analyser/database/sqlite_alchemy_orm/__init__.py
cytoskeleton_analyser/database/sqlite_alchemy_orm/db.py
cytoskeleton_analyser/database/sqlite_alchemy_orm/containers/__init__.py
cytoskeleton_analyser/database/sqlite_alchemy_orm/containers/cell_elements.py
cytoskeleton_analyser/database/sqlite_alchemy_orm/containers/config.py
cytoskeleton_analyser/database/sqlite_alchemy_orm/containers/container.py
cytoskeleton_analyser/database/sqlite_alchemy_orm/models/__init__.py
cytoskeleton_analyser/database/sqlite_alchemy_orm/models/config.py
cytoskeleton_analyser/database/sqlite_alchemy_orm/models/config_mtoc.py
cytoskeleton_analyser/database/sqlite_alchemy_orm/models/config_nucleus.py
cytoskeleton_analyser/database/sqlite_alchemy_orm/models/config_plasma.py
cytoskeleton_analyser/fitting/__init__.py
cytoskeleton_analyser/fitting/base.py
cytoskeleton_analyser/fitting/const.py
cytoskeleton_analyser/fitting/exponential.py
cytoskeleton_analyser/fitting/gamma.py
cytoskeleton_analyser/fitting/lognorm.py
cytoskeleton_analyser/fitting/normal.py
cytoskeleton_analyser/fitting/rayleigh.py
cytoskeleton_analyser/fitting/von_mises.py
cytoskeleton_analyser/fitting/weibull.py
cytoskeleton_analyser/history/__init__.py
cytoskeleton_analyser/history/cell_history.py
cytoskeleton_analyser/history/drivers.py
cytoskeleton_analyser/history/event_collections.py
cytoskeleton_analyser/history/filament_history.py
cytoskeleton_analyser-1.6.5.dist-info/LICENSE.txt
cytoskeleton_analyser-1.6.5.dist-info/METADATA
cytoskeleton_analyser-1.6.5.dist-info/WHEEL
cytoskeleton_analyser-1.6.5.dist-info/top_level.txt
cytoskeleton_analyser-1.6.5.dist-info/RECORD
