Metadata-Version: 2.1
Name: cytoskeleton-analyser
Version: 1.6.5
Summary: Examines simulated cell microtubules
Home-page: https://github.com/vsukhor/cytoskeleton-analyser
Author: Valerii Sukhorukov
Author-email: vsukhorukov@yahoo.com
Maintainer: Valerii Sukhorukov
Maintainer-email: vsukhorukov@yahoo.com
License: BSD-3-Clause
Project-URL: Source Code, https://github.com/vsukhor/cytoskeleton-analyser
Keywords: computational biology,cytoskeleton,cell,data analysis
Platform: UNKNOWN
Classifier: Intended Audience :: Science/Research
Classifier: License :: OSI Approved :: BSD License
Classifier: Operating System :: POSIX
Classifier: Programming Language :: Python
Classifier: Programming Language :: Python :: 3.9
Classifier: Topic :: Scientific/Engineering
Classifier: Topic :: Scientific/Engineering :: Bio-Informatics
Requires-Python: >=3.9
Requires-Dist: matplotlib (==3.3.4)
Requires-Dist: meshio (>=4.3.11)
Requires-Dist: scipy (>=1.6.0)
Requires-Dist: numpy (>=1.20.0)
Requires-Dist: SQLAlchemy (>=1.3.23)
